{"header":{"resultcode":"200","message":"success","total_rows":18},"body":{"item":[{"dara_profile_id":"5","dara_type_id":"3","belong_to_id":"0","nick_name":"Anne","first_name":"Anne","middle_name":null,"last_name":"Hathaway","pen_name":null,"avatar":"avatar20140925064259875.jpg","gender":"0","birth_date":"2014-09-24","dara_type_name":"\u0e14\u0e32\u0e23\u0e32\u0e2e\u0e2d\u0e25\u0e25\u0e35\u0e27\u0e39\u0e49\u0e14","belong_to":null,"tags":[]},{"dara_profile_id":"18","dara_type_id":"1","belong_to_id":"4","nick_name":"\u0e04\u0e23\u0e34\u0e2a \u0e2b\u0e2d\u0e27\u0e31\u0e07","first_name":"\u0e28\u0e34\u0e23\u0e34\u0e19\u0e16\u0e16","middle_name":"","last_name":"\u0e2b\u0e2d\u0e27\u0e31\u0e07","pen_name":"\u0e04\u0e23\u0e34\u0e2a \u0e2b\u0e2d\u0e27\u0e31\u0e07","avatar":"dara201411110251636.jpg","gender":"f","birth_date":"0000-00-00","dara_type_name":"\u0e14\u0e32\u0e23\u0e32\u0e44\u0e17\u0e22","belong_to":"GMM","tags":[{"pair_id":"178","tag_id":"21","ref_id":"18","ref_type":"5","order":null,"create_date":"2014-10-17 04:23:59","tag_text":"\u0e04\u0e23\u0e34\u0e2a \u0e2b\u0e2d\u0e27\u0e31\u0e07"},{"pair_id":"525","tag_id":"47","ref_id":"18","ref_type":"5","order":null,"create_date":"2014-11-26 10:08:20","tag_text":"\u0e04\u0e23\u0e34\u0e2a"}]},{"dara_profile_id":"26","dara_type_id":"1","belong_to_id":"0","nick_name":"\u0e08\u0e31\u0e4a\u0e01\u0e08\u0e31\u0e48\u0e19","first_name":"\u0e2d\u0e04\u0e31\u0e21\u0e22\u0e4c\u0e2a\u0e34\u0e23\u0e34","middle_name":null,"last_name":"\u0e2a\u0e38\u0e27\u0e23\u0e23\u0e13\u0e28\u0e38\u0e02","pen_name":null,"avatar":"dara201411060240625.jpg","gender":"f","birth_date":"0000-00-00","dara_type_name":"\u0e14\u0e32\u0e23\u0e32\u0e44\u0e17\u0e22","belong_to":null,"tags":[{"pair_id":"298","tag_id":"36","ref_id":"26","ref_type":"5","order":null,"create_date":"2014-11-06 02:40:17","tag_text":"\u0e2d\u0e04\u0e31\u0e21\u0e22\u0e4c\u0e2a\u0e34\u0e23\u0e34 \u0e2a\u0e38\u0e27\u0e23\u0e23\u0e13\u0e28\u0e38\u0e02"},{"pair_id":"299","tag_id":"37","ref_id":"26","ref_type":"5","order":null,"create_date":"2014-11-06 02:40:17","tag_text":"\u0e08\u0e31\u0e4a\u0e01\u0e08\u0e31\u0e48\u0e19"}]},{"dara_profile_id":"16","dara_type_id":"1","belong_to_id":"0","nick_name":"\u0e0b\u0e32\u0e23\u0e48\u0e32","first_name":"\u0e21\u0e32\u0e25\u0e32\u0e01\u0e38\u0e25","middle_name":"","last_name":"","pen_name":null,"avatar":"dara201411110255552.jpg","gender":"f","birth_date":"0000-00-00","dara_type_name":"\u0e14\u0e32\u0e23\u0e32\u0e44\u0e17\u0e22","belong_to":null,"tags":[{"pair_id":"192","tag_id":"26","ref_id":"16","ref_type":"5","order":null,"create_date":"2014-10-28 03:14:09","tag_text":"\u0e21\u0e32\u0e25\u0e32\u0e01\u0e38\u0e25"},{"pair_id":"193","tag_id":"27","ref_id":"16","ref_type":"5","order":null,"create_date":"2014-10-28 03:14:09","tag_text":"\u0e0b\u0e32\u0e23\u0e48\u0e32"}]},{"dara_profile_id":"21","dara_type_id":"1","belong_to_id":"0","nick_name":"\u0e0d\u0e32\u0e0d\u0e48\u0e32","first_name":"\u0e2d\u0e38\u0e23\u0e31\u0e2a\u0e22\u0e32","middle_name":null,"last_name":"\u0e2a\u0e40\u0e1b\u0e2d\u0e23\u0e4c\u0e1a\u0e31\u0e19\u0e14\u0e4c","pen_name":null,"avatar":"dara201410301023609.jpg","gender":"f","birth_date":"0000-00-00","dara_type_name":"\u0e14\u0e32\u0e23\u0e32\u0e44\u0e17\u0e22","belong_to":null,"tags":[{"pair_id":"241","tag_id":"28","ref_id":"21","ref_type":"5","order":null,"create_date":"2014-10-30 10:23:41","tag_text":"\u0e2d\u0e38\u0e23\u0e31\u0e2a\u0e22\u0e32 \u0e2a\u0e40\u0e1b\u0e2d\u0e23\u0e4c\u0e1a\u0e31\u0e19\u0e14\u0e4c"},{"pair_id":"242","tag_id":"29","ref_id":"21","ref_type":"5","order":null,"create_date":"2014-10-30 10:23:41","tag_text":"\u0e0d\u0e32\u0e0d\u0e48\u0e32"}]},{"dara_profile_id":"24","dara_type_id":"1","belong_to_id":"0","nick_name":"\u0e13\u0e40\u0e14\u0e0a\u0e19\u0e4c","first_name":"\u0e13\u0e40\u0e14\u0e0a\u0e19\u0e4c","middle_name":"","last_name":"\u0e04\u0e39\u0e01\u0e34\u0e21\u0e34\u0e22\u0e30","pen_name":null,"avatar":"dara201411101012208.jpg","gender":"m","birth_date":"0000-00-00","dara_type_name":"\u0e14\u0e32\u0e23\u0e32\u0e44\u0e17\u0e22","belong_to":null,"tags":[{"pair_id":"257","tag_id":"34","ref_id":"24","ref_type":"5","order":null,"create_date":"2014-11-04 03:30:03","tag_text":"\u0e13\u0e40\u0e14\u0e0a\u0e19\u0e4c \u0e04\u0e39\u0e01\u0e34\u0e21\u0e34\u0e22\u0e30"},{"pair_id":"258","tag_id":"35","ref_id":"24","ref_type":"5","order":null,"create_date":"2014-11-04 03:30:03","tag_text":"\u0e13\u0e40\u0e14\u0e0a\u0e19\u0e4c"}]},{"dara_profile_id":"2","dara_type_id":"1","belong_to_id":"0","nick_name":"\u0e14\u0e34\u0e27","first_name":"\u0e2d\u0e23\u0e34\u0e2a\u0e23\u0e32","middle_name":null,"last_name":"\u0e17\u0e2d\u0e07\u0e1a\u0e23\u0e34\u0e2a\u0e38\u0e17\u0e18\u0e34\u0e4c","pen_name":null,"avatar":"avatar20140924101103835.jpg","gender":"m","birth_date":"0000-00-00","dara_type_name":"\u0e14\u0e32\u0e23\u0e32\u0e44\u0e17\u0e22","belong_to":null,"tags":[{"pair_id":"125","tag_id":"12","ref_id":"2","ref_type":"5","order":null,"create_date":"2014-10-02 09:07:14","tag_text":"\u0e2d\u0e23\u0e34\u0e2a\u0e23\u0e32 \u0e17\u0e2d\u0e07\u0e1a\u0e23\u0e34\u0e2a\u0e38\u0e17\u0e18\u0e34\u0e4c"},{"pair_id":"126","tag_id":"13","ref_id":"2","ref_type":"5","order":null,"create_date":"2014-10-02 09:07:14","tag_text":"\u0e14\u0e34\u0e27"}]},{"dara_profile_id":"1","dara_type_id":"1","belong_to_id":"0","nick_name":"\u0e19\u0e38\u0e48\u0e19","first_name":"\u0e27\u0e23\u0e19\u0e38\u0e0a","middle_name":"","last_name":"\u0e20\u0e34\u0e23\u0e21\u0e22\u0e4c\u0e20\u0e31\u0e01\u0e14\u0e35","pen_name":null,"avatar":"avatar201409250945118.jpg","gender":"f","birth_date":"1980-01-02","dara_type_name":"\u0e14\u0e32\u0e23\u0e32\u0e44\u0e17\u0e22","belong_to":null,"tags":[{"pair_id":"121","tag_id":"8","ref_id":"1","ref_type":"5","order":null,"create_date":"2014-10-02 09:06:25","tag_text":"\u0e27\u0e23\u0e19\u0e38\u0e0a \u0e20\u0e34\u0e23\u0e21\u0e22\u0e4c\u0e20\u0e31\u0e01\u0e14\u0e35"},{"pair_id":"122","tag_id":"9","ref_id":"1","ref_type":"5","order":null,"create_date":"2014-10-02 09:06:25","tag_text":"\u0e19\u0e38\u0e48\u0e19"},{"pair_id":"129","tag_id":"16","ref_id":"1","ref_type":"5","order":null,"create_date":"2014-10-02 10:32:21","tag_text":"test test"},{"pair_id":"130","tag_id":"17","ref_id":"1","ref_type":"5","order":null,"create_date":"2014-10-02 10:32:21","tag_text":"test"}]},{"dara_profile_id":"22","dara_type_id":"1","belong_to_id":"0","nick_name":"\u0e19\u0e49\u0e33\u0e2b\u0e27\u0e32\u0e19","first_name":"\u0e0a\u0e19\u0e19\u0e31\u0e19\u0e17\u0e4c","middle_name":"","last_name":"","pen_name":null,"avatar":"dara201411030918125.jpg","gender":"f","birth_date":"1990-02-22","dara_type_name":"\u0e14\u0e32\u0e23\u0e32\u0e44\u0e17\u0e22","belong_to":null,"tags":[{"pair_id":"250","tag_id":"31","ref_id":"22","ref_type":"5","order":null,"create_date":"2014-11-03 09:18:05","tag_text":"\u0e0a\u0e19\u0e19\u0e31\u0e19\u0e17\u0e4c"},{"pair_id":"251","tag_id":"32","ref_id":"22","ref_type":"5","order":null,"create_date":"2014-11-03 09:18:05","tag_text":"\u0e19\u0e49\u0e33\u0e2b\u0e27\u0e32\u0e19"}]},{"dara_profile_id":"9","dara_type_id":"1","belong_to_id":"0","nick_name":"\u0e1b\u0e35\u0e43\u0e2b\u0e21\u0e48","first_name":"\u0e2a\u0e38\u0e21\u0e19\u0e15\u0e4c\u0e23\u0e31\u0e15\u0e19\u0e4c","middle_name":"","last_name":"\u0e27\u0e31\u0e12\u0e19\u0e32\u0e40\u0e28\u0e25\u0e32\u0e23\u0e31\u0e15\u0e19\u0e4c","pen_name":null,"avatar":"dara201411110933394.jpg","gender":"f","birth_date":"1984-11-28","dara_type_name":"\u0e14\u0e32\u0e23\u0e32\u0e44\u0e17\u0e22","belong_to":null,"tags":[{"pair_id":"127","tag_id":"14","ref_id":"9","ref_type":"5","order":null,"create_date":"2014-10-02 09:07:22","tag_text":"\u0e2a\u0e38\u0e21\u0e19\u0e15\u0e4c\u0e23\u0e31\u0e15\u0e19\u0e4c \u0e27\u0e31\u0e12\u0e19\u0e32\u0e40\u0e28\u0e25\u0e32\u0e23\u0e31\u0e15\u0e19\u0e4c"},{"pair_id":"128","tag_id":"15","ref_id":"9","ref_type":"5","order":null,"create_date":"2014-10-02 09:07:22","tag_text":"\u0e1b\u0e35\u0e43\u0e2b\u0e21\u0e48"}]},{"dara_profile_id":"6","dara_type_id":"1","belong_to_id":"0","nick_name":"\u0e1b\u0e39","first_name":"\u0e44\u0e1b\u0e23\u0e22\u0e32","middle_name":"\u0e25\u0e38\u0e19\u0e14\u0e4c\u0e40\u0e1a\u0e34\u0e23\u0e4c\u0e01","last_name":"\u0e2a\u0e27\u0e19\u0e14\u0e2d\u0e01\u0e44\u0e21\u0e49","pen_name":null,"avatar":"dara201411100922251.jpg","gender":"f","birth_date":"1986-03-17","dara_type_name":"\u0e14\u0e32\u0e23\u0e32\u0e44\u0e17\u0e22","belong_to":null,"tags":[{"pair_id":"123","tag_id":"10","ref_id":"6","ref_type":"5","order":null,"create_date":"2014-10-02 09:06:48","tag_text":"\u0e44\u0e1b\u0e23\u0e22\u0e32 \u0e2a\u0e27\u0e19\u0e14\u0e2d\u0e01\u0e44\u0e21\u0e49"},{"pair_id":"124","tag_id":"11","ref_id":"6","ref_type":"5","order":null,"create_date":"2014-10-02 09:06:48","tag_text":"\u0e1b\u0e39 \u0e44\u0e1b\u0e23\u0e22\u0e32"},{"pair_id":"311","tag_id":"38","ref_id":"6","ref_type":"5","order":null,"create_date":"2014-11-10 05:05:07","tag_text":"\u0e25\u0e38\u0e19\u0e14\u0e4c\u0e40\u0e1a\u0e34\u0e23\u0e4c\u0e01"},{"pair_id":"312","tag_id":"39","ref_id":"6","ref_type":"5","order":null,"create_date":"2014-11-10 05:05:07","tag_text":"\u0e2a\u0e27\u0e19\u0e14\u0e2d\u0e01\u0e44\u0e21\u0e49"}]},{"dara_profile_id":"29","dara_type_id":"1","belong_to_id":"0","nick_name":"\u0e25\u0e35\u0e40\u0e14\u0e35\u0e22","first_name":"\u0e28\u0e23\u0e31\u0e13\u0e22\u0e4c\u0e23\u0e31\u0e0a\u0e15\u0e4c","middle_name":"","last_name":"\u0e27\u0e34\u0e2a\u0e38\u0e17\u0e18\u0e34\u0e18\u0e32\u0e14\u0e32","pen_name":null,"avatar":"dara201411180801509.jpg","gender":"f","birth_date":"0000-00-00","dara_type_name":"\u0e14\u0e32\u0e23\u0e32\u0e44\u0e17\u0e22","belong_to":null,"tags":[{"pair_id":"398","tag_id":"42","ref_id":"29","ref_type":"5","order":null,"create_date":"2014-11-18 08:01:04","tag_text":"\u0e28\u0e23\u0e31\u0e13\u0e22\u0e4c\u0e23\u0e31\u0e0a\u0e15\u0e4c \u0e27\u0e34\u0e2a\u0e38\u0e17\u0e18\u0e34\u0e18\u0e32\u0e14\u0e32"},{"pair_id":"399","tag_id":"43","ref_id":"29","ref_type":"5","order":null,"create_date":"2014-11-18 08:01:04","tag_text":"\u0e25\u0e35\u0e40\u0e14\u0e35\u0e22"}]},{"dara_profile_id":"30","dara_type_id":"1","belong_to_id":"2","nick_name":"\u0e2d\u0e31\u0e49\u0e21","first_name":"\u0e1e\u0e31\u0e0a\u0e23\u0e32\u0e20\u0e32","middle_name":"","last_name":"\u0e44\u0e0a\u0e22\u0e40\u0e0a\u0e37\u0e49\u0e2d","pen_name":"","avatar":"dara201411210823858.jpg","gender":"f","birth_date":"1978-12-05","dara_type_name":"\u0e14\u0e32\u0e23\u0e32\u0e44\u0e17\u0e22","belong_to":"\u0e0a\u0e48\u0e2d\u0e07 7","tags":[{"pair_id":"451","tag_id":"45","ref_id":"30","ref_type":"5","order":null,"create_date":"2014-11-21 08:23:40","tag_text":"\u0e1e\u0e31\u0e0a\u0e23\u0e32\u0e20\u0e32 \u0e44\u0e0a\u0e22\u0e40\u0e0a\u0e37\u0e49\u0e2d"},{"pair_id":"452","tag_id":"46","ref_id":"30","ref_type":"5","order":null,"create_date":"2014-11-21 08:23:40","tag_text":"\u0e2d\u0e31\u0e49\u0e21"}]},{"dara_profile_id":"17","dara_type_id":"1","belong_to_id":"0","nick_name":"\u0e41\u0e15\u0e49\u0e27","first_name":"\u0e13\u0e10\u0e1e\u0e23","middle_name":null,"last_name":"\u0e40\u0e15\u0e21\u0e35\u0e23\u0e31\u0e01\u0e29\u0e4c","pen_name":null,"avatar":"dara201411050411757.jpg","gender":"f","birth_date":"0000-00-00","dara_type_name":"\u0e14\u0e32\u0e23\u0e32\u0e44\u0e17\u0e22","belong_to":null,"tags":[{"pair_id":"167","tag_id":"18","ref_id":"17","ref_type":"5","order":null,"create_date":"2014-10-16 07:05:57","tag_text":"\u0e13\u0e10\u0e1e\u0e23 \u0e40\u0e15\u0e21\u0e35\u0e23\u0e31\u0e01\u0e29\u0e4c"},{"pair_id":"168","tag_id":"19","ref_id":"17","ref_type":"5","order":null,"create_date":"2014-10-16 07:05:57","tag_text":"\u0e41\u0e15\u0e49\u0e27"}]},{"dara_profile_id":"23","dara_type_id":"1","belong_to_id":"0","nick_name":"\u0e42\u0e1a\u0e27\u0e35\u0e48","first_name":"","middle_name":null,"last_name":"","pen_name":null,"avatar":"dara201411040325972.jpg","gender":"f","birth_date":"0000-00-00","dara_type_name":"\u0e14\u0e32\u0e23\u0e32\u0e44\u0e17\u0e22","belong_to":null,"tags":[{"pair_id":"256","tag_id":"33","ref_id":"23","ref_type":"5","order":null,"create_date":"2014-11-04 03:25:44","tag_text":"\u0e42\u0e1a\u0e27\u0e35\u0e48"}]},{"dara_profile_id":"7","dara_type_id":"1","belong_to_id":"0","nick_name":"\u0e42\u0e2d\u0e0b\u0e32 \u0e41\u0e27\u0e07","first_name":"\u0e42\u0e2d\u0e0b\u0e32 \u0e41\u0e27\u0e07","middle_name":null,"last_name":"","pen_name":null,"avatar":"avatar201409250914727.jpg","gender":"m","birth_date":"0000-00-00","dara_type_name":"\u0e14\u0e32\u0e23\u0e32\u0e44\u0e17\u0e22","belong_to":null,"tags":[]},{"dara_profile_id":"19","dara_type_id":"1","belong_to_id":"0","nick_name":"\u0e43\u0e1a\u0e40\u0e1f\u0e34\u0e23\u0e4c\u0e19","first_name":"\u0e1e\u0e34\u0e21\u0e1e\u0e4c\u0e0a\u0e19\u0e01","middle_name":"","last_name":"\u0e25\u0e37\u0e2d\u0e27\u0e34\u0e40\u0e28\u0e29\u0e44\u0e1e\u0e1a\u0e39\u0e25\u0e22\u0e4c","pen_name":null,"avatar":"dara201411101004105.jpg","gender":"f","birth_date":"0000-00-00","dara_type_name":"\u0e14\u0e32\u0e23\u0e32\u0e44\u0e17\u0e22","belong_to":null,"tags":[{"pair_id":"185","tag_id":"22","ref_id":"19","ref_type":"5","order":null,"create_date":"2014-10-20 05:41:13","tag_text":"\u0e1e\u0e34\u0e21\u0e1e\u0e4c\u0e0a\u0e19\u0e01 \u0e25\u0e37\u0e2d\u0e27\u0e34\u0e40\u0e28\u0e29\u0e44\u0e1e\u0e1a\u0e39\u0e25\u0e22\u0e4c"},{"pair_id":"186","tag_id":"23","ref_id":"19","ref_type":"5","order":null,"create_date":"2014-10-20 05:41:13","tag_text":"\u0e43\u0e1a\u0e40\u0e1f\u0e34\u0e23\u0e4c\u0e19"}]},{"dara_profile_id":"20","dara_type_id":"1","belong_to_id":"2,3","nick_name":"\u0e43\u0e2b\u0e21\u0e48","first_name":"\u0e14\u0e32\u0e27\u0e34\u0e01\u0e32","middle_name":"","last_name":"\u0e42\u0e2e\u0e23\u0e4c\u0e40\u0e19\u0e48","pen_name":"","avatar":"dara201411100910663.jpg","gender":"f","birth_date":"0000-00-00","dara_type_name":"\u0e14\u0e32\u0e23\u0e32\u0e44\u0e17\u0e22","belong_to":"\u0e0a\u0e48\u0e2d\u0e07 7","tags":[{"pair_id":"187","tag_id":"24","ref_id":"20","ref_type":"5","order":null,"create_date":"2014-10-20 06:12:32","tag_text":"\u0e14\u0e32\u0e27\u0e34\u0e01\u0e32 \u0e42\u0e2e\u0e23\u0e4c\u0e40\u0e19\u0e48"},{"pair_id":"188","tag_id":"25","ref_id":"20","ref_type":"5","order":null,"create_date":"2014-10-20 06:12:32","tag_text":"\u0e43\u0e2b\u0e21\u0e48"}]}]}}